{"background":{"class":"border_1"},"controls":{"l":"false","r":"false","t":"false","b":"false"},"subtitle":{"selector":"subtitle","text":"table.component"},"code":[{"type":"html","class":"","code":"<table class=\"table table-sm table-striped table-bordered table-hover\">\n    <thead class=\"thead-inverse\">\n        <tr>\n            <th>id</th>\n            <th>item</th>\n            <th>text</th>\n            <th>date</th>\n        </tr>\n    </thead>\n    <tbody>\n        <tr *ngFor=\"let d of data\">\n            <td>{{d.id}}</td>\n            <td>{{d.item}}</td>\n            <td>{{d.text}}</td>\n            <td>{{d.date}}</td>\n        </tr>\n    </tbody>\n</table>\n","filename":"table.component.html"}]}